{
  "configById": {
    "3D!1jl2if2": {
      "cameraState": {
        "perspective": true,
        "distance": 1.3888568037374944,
        "phi": 64.69756619512403,
        "thetaOffset": -148.07054144022032,
        "targetOffset": [
          0.23340814513278244,
          0.34402130995358426,
          1.0027539110044606e-16
        ],
        "target": [
          0,
          0,
          0
        ],
        "targetOrientation": [
          0,
          0,
          0,
          1
        ],
        "fovy": 45,
        "near": 0.5,
        "far": 5000
      },
      "followMode": "follow-pose",
      "scene": {
        "transforms": {
          "showLabel": false,
          "axisScale": 0.3,
          "editable": false,
          "enablePreloading": false,
          "lineWidth": 0
        },
        "enableStats": true,
        "meshUpAxis": "y_up"
      },
      "transforms": {
        "frame:link0": {
          "visible": false
        },
        "frame:link1": {
          "visible": false
        },
        "frame:link2": {
          "visible": false
        },
        "frame:link3": {
          "visible": false
        },
        "frame:link4": {
          "visible": false
        },
        "frame:link5": {
          "visible": false
        },
        "frame:link6": {
          "visible": false
        },
        "frame:link7": {
          "visible": false
        },
        "frame:link8": {
          "visible": false
        },
        "frame:seg1_mid_link_3": {
          "visible": true
        },
        "frame:head_base_link": {
          "visible": true
        },
        "frame:seg1_end_link": {
          "visible": true
        }
      },
      "topics": {
        "/robot_description": {
          "visible": true
        },
        "/initialpose": {
          "visible": false
        }
      },
      "layers": {},
      "publish": {
        "type": "point",
        "poseTopic": "/move_base_simple/goal",
        "pointTopic": "/clicked_point",
        "poseEstimateTopic": "/initialpose",
        "poseEstimateXDeviation": 0.5,
        "poseEstimateYDeviation": 0.5,
        "poseEstimateThetaDeviation": 0.26179939
      },
      "imageMode": {},
      "followTf": "world"
    },
    "Publish!2ofpjm7": {
      "buttonText": "Publish",
      "buttonTooltip": "",
      "advancedView": true,
      "value": "{\n  \"interface_names\": [\"segment1_dx\", \"segment1_dy\", \"segment1_l\"],\n  \"values\": [0.0, 0.0, 0.22]\n}",
      "topicName": "/helix/command/configuration",
      "datatype": "control_msgs/msg/InterfaceValue"
    },
    "Publish!4l73s70": {
      "buttonText": "Publish",
      "buttonTooltip": "",
      "advancedView": true,
      "value": "{\n  \"interface_names\": [\"tendon6\", \"tendon7\", \"tendon8\"],\n  \"values\": [0.24, 0.23, 0.19]\n}",
      "topicName": "/helix/command/tendon_lengths",
      "datatype": "control_msgs/msg/InterfaceValue"
    },
    "Publish!3ydn2as": {
      "buttonText": "Publish",
      "buttonTooltip": "",
      "advancedView": true,
      "value": "{\n  \"interface_names\": [\"segment0_dx\", \"segment0_dy\", \"segment0_l\", \"segment1_dx\", \"segment1_dy\", \"segment1_l\", \"segment2_dx\", \"segment2_dy\", \"segment2_l\"],\n  \"values\": [0.0, 0.0, 0.125, 0.0, 0.0, 0.25, 0.0, 0.0, 0.25]\n}",
      "topicName": "/helix/command/configuration",
      "datatype": "control_msgs/msg/InterfaceValue",
      "lichtblickPanelTitle": "Reset to Calibration Pose"
    },
    "CallService!vc17zy": {
      "requestPayload": "{}",
      "layout": "vertical",
      "serviceName": "/helix/start_calibration"
    },
    "CallService!bz4wvt": {
      "requestPayload": "{}",
      "layout": "vertical",
      "serviceName": "/helix/finish_calibration"
    },
    "Indicator!3klgh57": {
      "path": "/helix/status/node_count.data",
      "style": "bulb",
      "fallbackColor": "#d9ef00",
      "fallbackLabel": "Initializing",
      "rules": [
        {
          "operator": "=",
          "rawValue": "8",
          "color": "#68e24a",
          "label": "Running"
        }
      ],
      "lichtblickPanelTitle": "System Status"
    },
    "Plot!406fz6h": {
      "paths": [
        {
          "timestampMethod": "receiveTime",
          "value": "/helix/estimated/tendon_lengths.values[0]",
          "enabled": true
        },
        {
          "timestampMethod": "receiveTime",
          "value": "/helix/estimated/tendon_lengths.values[1]",
          "enabled": true
        },
        {
          "timestampMethod": "receiveTime",
          "value": "/helix/estimated/tendon_lengths.values[2]",
          "enabled": true
        }
      ],
      "minYValue": 0.05,
      "maxYValue": 0.15,
      "showXAxisLabels": true,
      "showYAxisLabels": true,
      "showLegend": true,
      "legendDisplay": "floating",
      "showPlotValuesInLegend": false,
      "isSynced": true,
      "xAxisVal": "timestamp",
      "sidebarDimension": 240,
      "followingViewWidth": 30
    },
    "Plot!1jwj4zq": {
      "paths": [
        {
          "timestampMethod": "receiveTime",
          "value": "/helix/estimated/tendon_lengths.values[6]",
          "enabled": true
        },
        {
          "timestampMethod": "receiveTime",
          "value": "/helix/estimated/tendon_lengths.values[7]",
          "enabled": true
        },
        {
          "timestampMethod": "receiveTime",
          "value": "/helix/estimated/tendon_lengths.values[8]",
          "enabled": true
        }
      ],
      "minYValue": 0.1,
      "maxYValue": 0.3,
      "showXAxisLabels": true,
      "showYAxisLabels": true,
      "showLegend": true,
      "legendDisplay": "floating",
      "showPlotValuesInLegend": false,
      "isSynced": true,
      "xAxisVal": "timestamp",
      "sidebarDimension": 240,
      "followingViewWidth": 30
    },
    "Plot!3d9xcgn": {
      "paths": [
        {
          "timestampMethod": "receiveTime",
          "value": "/helix/estimated/tendon_lengths.values[3]",
          "enabled": true
        },
        {
          "timestampMethod": "receiveTime",
          "value": "/helix/estimated/tendon_lengths.values[4]",
          "enabled": true
        },
        {
          "timestampMethod": "receiveTime",
          "value": "/helix/estimated/tendon_lengths.values[5]",
          "enabled": true
        }
      ],
      "minYValue": 0.1,
      "maxYValue": 0.3,
      "showXAxisLabels": true,
      "showYAxisLabels": true,
      "showLegend": true,
      "legendDisplay": "floating",
      "showPlotValuesInLegend": false,
      "isSynced": true,
      "xAxisVal": "timestamp",
      "sidebarDimension": 240,
      "followingViewWidth": 30
    },
    "Teleop!4jc6mai": {
      "topic": "/web/teleop/xy",
      "publishRate": 10,
      "upButton": {
        "field": "linear-x",
        "value": 1
      },
      "downButton": {
        "field": "linear-x",
        "value": -1
      },
      "leftButton": {
        "field": "linear-y",
        "value": 1
      },
      "rightButton": {
        "field": "linear-y",
        "value": -1
      },
      "lichtblickPanelTitle": "X-Y-Motion"
    },
    "Teleop!3lk1t5k": {
      "topic": "/web/teleop/z",
      "publishRate": 10,
      "upButton": {
        "field": "linear-z",
        "value": 1
      },
      "downButton": {
        "field": "linear-z",
        "value": -1
      },
      "leftButton": {
        "field": "angular-z",
        "value": 1
      },
      "rightButton": {
        "field": "angular-z",
        "value": -1
      },
      "lichtblickPanelTitle": "Z-Motion"
    },
    "Teleop!3pqx63y": {
      "topic": "/web/teleop/pitchyaw",
      "publishRate": 10,
      "upButton": {
        "field": "angular-x",
        "value": 1
      },
      "downButton": {
        "field": "angular-x",
        "value": -1
      },
      "leftButton": {
        "field": "angular-z",
        "value": 1
      },
      "rightButton": {
        "field": "angular-z",
        "value": -1
      },
      "lichtblickPanelTitle": "Tip Orientation (xy-axis)"
    },
    "RosOut!ylwn5k": {
      "searchTerms": [],
      "minLogLevel": 2
    },
    "CallService!27fnkct": {
      "requestPayload": "{\"data\": \"velocity_control\"}",
      "layout": "vertical",
      "serviceName": "/helix/dynamixel_driver_node/switch_control_mode"
    },
    "Teleop!3f7x1tn": {
      "topic": "/web/command/dynamixel0",
      "publishRate": 1,
      "upButton": {
        "field": "linear-x",
        "value": 1
      },
      "downButton": {
        "field": "linear-x",
        "value": -1
      },
      "leftButton": {
        "field": "angular-z",
        "value": 1
      },
      "rightButton": {
        "field": "angular-z",
        "value": -1
      },
      "lichtblickPanelTitle": "/web/command/dynamixel0"
    },
    "Teleop!3kebb81": {
      "topic": "/web/command/dynamixel1",
      "publishRate": 1,
      "upButton": {
        "field": "linear-x",
        "value": 1
      },
      "downButton": {
        "field": "linear-x",
        "value": -1
      },
      "leftButton": {
        "field": "angular-z",
        "value": 1
      },
      "rightButton": {
        "field": "angular-z",
        "value": -1
      },
      "lichtblickPanelTitle": "/web/command/dynamixel1"
    },
    "Teleop!3nzuoei": {
      "topic": "/web/command/dynamixel2",
      "publishRate": 1,
      "upButton": {
        "field": "linear-x",
        "value": 1
      },
      "downButton": {
        "field": "linear-x",
        "value": -1
      },
      "leftButton": {
        "field": "angular-z",
        "value": 1
      },
      "rightButton": {
        "field": "angular-z",
        "value": -1
      },
      "lichtblickPanelTitle": "/web/command/dynamixel2"
    },
    "Teleop!330ivjc": {
      "topic": "/web/command/dynamixel3",
      "publishRate": 1,
      "upButton": {
        "field": "linear-x",
        "value": 1
      },
      "downButton": {
        "field": "linear-x",
        "value": -1
      },
      "leftButton": {
        "field": "angular-z",
        "value": 1
      },
      "rightButton": {
        "field": "angular-z",
        "value": -1
      },
      "lichtblickPanelTitle": "/web/command/dynamixel3"
    },
    "Teleop!hl4hjg": {
      "topic": "/web/command/dynamixel4",
      "publishRate": 1,
      "upButton": {
        "field": "linear-x",
        "value": 1
      },
      "downButton": {
        "field": "linear-x",
        "value": -1
      },
      "leftButton": {
        "field": "angular-z",
        "value": 1
      },
      "rightButton": {
        "field": "angular-z",
        "value": -1
      },
      "lichtblickPanelTitle": "/web/command/dynamixel4"
    },
    "Teleop!36dzmh2": {
      "topic": "/web/command/dynamixel5",
      "publishRate": 1,
      "upButton": {
        "field": "linear-x",
        "value": 1
      },
      "downButton": {
        "field": "linear-x",
        "value": -1
      },
      "leftButton": {
        "field": "angular-z",
        "value": 1
      },
      "rightButton": {
        "field": "angular-z",
        "value": -1
      },
      "lichtblickPanelTitle": "/web/command/dynamixel5"
    },
    "Teleop!nxyg2s": {
      "topic": "/web/command/dynamixel6",
      "publishRate": 1,
      "upButton": {
        "field": "linear-x",
        "value": 1
      },
      "downButton": {
        "field": "linear-x",
        "value": -1
      },
      "leftButton": {
        "field": "angular-z",
        "value": 1
      },
      "rightButton": {
        "field": "angular-z",
        "value": -1
      },
      "lichtblickPanelTitle": "/web/command/dynamixel6"
    },
    "Teleop!1cji5ni": {
      "topic": "/web/command/dynamixel7",
      "publishRate": 1,
      "upButton": {
        "field": "linear-x",
        "value": 1
      },
      "downButton": {
        "field": "linear-x",
        "value": -1
      },
      "leftButton": {
        "field": "angular-z",
        "value": 1
      },
      "rightButton": {
        "field": "angular-z",
        "value": -1
      },
      "lichtblickPanelTitle": "/web/command/dynamixel7"
    },
    "Teleop!2g7fn20": {
      "topic": "/web/command/dynamixel8",
      "publishRate": 1,
      "upButton": {
        "field": "linear-x",
        "value": 1
      },
      "downButton": {
        "field": "linear-x",
        "value": -1
      },
      "leftButton": {
        "field": "angular-z",
        "value": 1
      },
      "rightButton": {
        "field": "angular-z",
        "value": -1
      },
      "lichtblickPanelTitle": "/web/command/dynamixel8"
    },
    "Tab!1u4cijz": {
      "activeTabIdx": 1,
      "tabs": [
        {
          "title": "Main",
          "layout": {
            "first": {
              "first": {
                "first": "3D!1jl2if2",
                "second": {
                  "first": "Publish!2ofpjm7",
                  "second": "Publish!4l73s70",
                  "direction": "row"
                },
                "direction": "column",
                "splitPercentage": 76.70011148272017
              },
              "second": "Publish!3ydn2as",
              "direction": "column",
              "splitPercentage": 80.59299191374663
            },
            "second": {
              "first": {
                "first": "CallService!vc17zy",
                "second": {
                  "first": "CallService!bz4wvt",
                  "second": "Indicator!3klgh57",
                  "direction": "row"
                },
                "direction": "row",
                "splitPercentage": 36.19281908872759
              },
              "second": {
                "first": "Plot!406fz6h",
                "second": {
                  "first": {
                    "first": "Plot!1jwj4zq",
                    "second": "Plot!3d9xcgn",
                    "direction": "column"
                  },
                  "second": {
                    "first": "Teleop!4jc6mai",
                    "second": {
                      "first": "Teleop!3lk1t5k",
                      "second": "Teleop!3pqx63y",
                      "direction": "row"
                    },
                    "direction": "row"
                  },
                  "direction": "column",
                  "splitPercentage": 66.20356150150276
                },
                "direction": "column",
                "splitPercentage": 34.880285056272555
              },
              "direction": "column",
              "splitPercentage": 28.505627254160693
            },
            "direction": "row"
          }
        },
        {
          "title": "Debug",
          "layout": {
            "first": {
              "first": "RosOut!ylwn5k",
              "second": "CallService!27fnkct",
              "direction": "column",
              "splitPercentage": 67.56513926325248
            },
            "second": {
              "first": {
                "first": "Teleop!3f7x1tn",
                "second": {
                  "first": "Teleop!3kebb81",
                  "second": "Teleop!3nzuoei",
                  "direction": "column"
                },
                "direction": "column",
                "splitPercentage": 29.559748427672954
              },
              "second": {
                "first": {
                  "first": "Teleop!330ivjc",
                  "second": {
                    "first": "Teleop!hl4hjg",
                    "second": "Teleop!36dzmh2",
                    "direction": "column"
                  },
                  "direction": "column",
                  "splitPercentage": 29.73944294699012
                },
                "second": {
                  "first": "Teleop!nxyg2s",
                  "second": {
                    "first": "Teleop!1cji5ni",
                    "second": "Teleop!2g7fn20",
                    "direction": "column"
                  },
                  "direction": "column",
                  "splitPercentage": 29.380053908355798
                },
                "direction": "row"
              },
              "direction": "row",
              "splitPercentage": 35.44612384202827
            },
            "direction": "row"
          }
        }
      ]
    }
  },
  "globalVariables": {
    "globalVariable": 4
  },
  "userNodes": {},
  "linkedGlobalVariables": [],
  "playbackConfig": {
    "speed": 1
  },
  "layout": "Tab!1u4cijz"
}
